snail_sdk/__init__.py
snail_sdk-0.7.5.dist-info/METADATA
snail_sdk-0.7.5.dist-info/WHEEL
snail_sdk-0.7.5.dist-info/licenses/LICENSE
snail_sdk-0.7.5.dist-info/RECORD
