Metadata-Version: 2.1
Name: snail_sdk
Version: 0.7.5
Summary: SDK for snail
Project-URL: Homepage, https://github.com/JoelEinbinder/snail
Project-URL: Bug Tracker, https://github.com/JoelEinbinder/snail/issues
Author-email: Joel Einbinder <joel.einbinder@gmail.com>
License-File: LICENSE
Classifier: License :: OSI Approved :: MIT License
Classifier: Operating System :: OS Independent
Classifier: Programming Language :: Python :: 3
Requires-Python: >=3.7
